HectareaDictionaryEncryption/__init__.py
HectareaDictionaryEncryption-4.20.68.9.9.9.dist-info/METADATA
HectareaDictionaryEncryption-4.20.68.9.9.9.dist-info/WHEEL
HectareaDictionaryEncryption-4.20.68.9.9.9.dist-info/top_level.txt
HectareaDictionaryEncryption-4.20.68.9.9.9.dist-info/RECORD
