Metadata-Version: 2.1
Name: HectareaDictionaryEncryption
Version: 4.20.68.9.9.9
Summary: HectareaDictionaryEncryption
Home-page: https://hectarea.netlify.app/
Author: Héctarea
Author-email: gonzalez.craqenll@gmail.com
License: MIT
Download-URL: https://github.com/Hectarea/DictionaryEncryption/archive/refs/tags/4.20.68.9.9.tar.gz
Keywords: Encryption,Dictionary,Hectarea,Secrets
Platform: UNKNOWN
